Workbook
Name RejRate: Inputs!$B$5
Name WageCoef: Inputs!$B$6
Name GoldPrice: Inputs!$B$7
Name PriceMin: Inputs!$B$8
Name PriceMax: Inputs!$B$9
Name TierQty: Inputs!$A$14:$A$18
Name TierSpecs: Inputs!$B$13:$D$13
Name TierPrices: Inputs!$B$14:$D$18
Name FixedTotal: Inputs!$B$28

Sheet Inputs
A1: Ball Bearing Contract Auction: inputs
A2: Blue text on a light-blue fill = input you can change. Yellow fill = value to confirm. Black = formula. All values from the case brief.
A4: Production rules
A5: Rejection rate (share of BBs produced that fail inspection) | B5: 0.15 | C5: Production = ROUNDUP(accepted / (1 - rate), 0). Customer pays for accepted BBs only.
A6: Wage coefficient (wages = raw materials used x coefficient) | B6: 1.8
A7: Gold price per BB (flat, announced after the auction) | B7: 5500 | C7: Pick 4,500 / 5,000 / 5,500 from the dropdown. Default 5,500 until announced.
A8: Contract price range: minimum per BB | B8: 16000 | C8: Prices outside this range are flagged orange on the Contracts sheets.
A9: Contract price range: maximum per BB | B9: 26000
A11: Raw-material price per BB (all-units tiers)
A12: The tier reached by one contract's purchase-order quantity (= its production quantity) sets the price for every BB in that order.
A13: Qty ordered (lower bound) | B13: Blue | C13: Silver | D13: Copper
A14: 1 | B14: 7000 | C14: 6500 | D14: 5500
A15: 11 | B15: 6500 | C15: 6000 | D15: 5000
A16: 21 | B16: 5500 | C16: 5500 | D16: 4000
A17: 31 | B17: 5000 | C17: 4500 | D17: 3000
A18: 41 | B18: 4000 | C18: 3500 | D18: 2000
A19: Gold does not use this table; it uses the Gold price in B7.
A21: Fixed operating expenses per year
A22: Factory rent | B22: 50000
A23: Management & administration | B23: 40000
A24: Machine maintenance | B24: 35000
A25: Utilities & insurance | B25: 20000
A26: Office & marketing | B26: 15000
A27: Depreciation | B27: 40000
A28: Total fixed operating expenses | B28: =SUM(B22:B27)
A30: Market size
A31: Year 1 market size | B31: 5300000
A32: Year 2 growth over Year 1 | B32: 0.2
A33: Year 3 growth over Year 2 | B33: 0.1
A34: Year 2 market size | B34: =B31*(1+B32)
A35: Year 3 market size | B35: =B34*(1+B33)

Sheet Summary
A1: Three-year summary
A2: Links to the Year total column of each P&L sheet. Years 2 and 3 fill in as contracts are typed into Contracts Y2 / Y3.
A4: ($) | B4: Year 1 | C4: Year 2 | D4: Year 3
A5: Revenue | B5: ='P&L Y1'!$B$6 | C5: ='P&L Y2'!$B$6 | D5: ='P&L Y3'!$B$6
A6: Contribution margin | B6: ='P&L Y1'!$B$10 | C6: ='P&L Y2'!$B$10 | D6: ='P&L Y3'!$B$10
A7: Fixed operating expenses | B7: ='P&L Y1'!$B$11 | C7: ='P&L Y2'!$B$11 | D7: ='P&L Y3'!$B$11
A8: Operating profit | B8: ='P&L Y1'!$B$12 | C8: ='P&L Y2'!$B$12 | D8: ='P&L Y3'!$B$12
A9: CM % | B9: =IF(B5=0,"",B6/B5) | C9: =IF(C5=0,"",C6/C5) | D9: =IF(D5=0,"",D6/D5)
A10: Operating margin % | B10: =IF(B5=0,"",B8/B5) | C10: =IF(C5=0,"",C8/C5) | D10: =IF(D5=0,"",D8/D5)
A11: Cumulative operating profit | B11: =SUM($B8:B8) | C11: =SUM($B8:C8) | D11: =SUM($B8:D8)
A12: Market size | B12: =Inputs!$B$31 | C12: =Inputs!$B$34 | D12: =Inputs!$B$35
A13: Share of market | B13: ='P&L Y1'!$B$15 | C13: ='P&L Y2'!$B$15 | D13: ='P&L Y3'!$B$15
A15: Fixed operating expenses are charged every year, so a year with no contracts entered still shows an operating loss equal to fixed expenses.

Sheet Contracts Y1
A1: Year 1 contracts won
A2: Type Contract ID, Spec, Accepted qty and Price (blue cells) in any empty row; every other column calculates. Each contract is its own purchase order.
A3: Orange price = outside the case price range (Inputs B8:B9). Other direct defaults to 0.
A4: Contract ID | B4: Spec | C4: Accepted qty (BB) | D4: Price per BB ($) | E4: Production qty (BB) | F4: Rejected qty (BB) | G4: RM price per BB ($) | H4: Revenue ($) | I4: Raw materials ($) | J4: Wages ($) | K4: Other direct ($) | L4: Contribution margin ($) | M4: CM % | N4: Break-even price per accepted BB ($) | O4: Price vs break-even ($)
A5: C05 | B5: Silver | C5: 15 | D5: 18000 | E5: =IF($A5="","",ROUNDUP(C5/(1-RejRate),0)) | F5: =IF($A5="","",E5-C5) | G5: =IF($A5="","",IF(B5="Gold",GoldPrice,INDEX(TierPrices,MATCH(E5,TierQty,1),MATCH(B5,TierSpecs,0)))) | H5: =IF($A5="","",C5*D5) | I5: =IF($A5="","",E5*G5) | J5: =IF($A5="","",I5*WageCoef) | K5: 0 | L5: =IF($A5="","",H5-I5-J5-N(K5)) | M5: =IF(OR($A5="",N(H5)=0),"",L5/H5) | N5: =IF(OR($A5="",N(C5)=0),"",(E5*G5*(1+WageCoef)+N(K5))/C5) | O5: =IF(OR($A5="",N5=""),"",D5-N5)
A6: C08 | B6: Silver | C6: 40 | D6: 11000 | E6: =IF($A6="","",ROUNDUP(C6/(1-RejRate),0)) | F6: =IF($A6="","",E6-C6) | G6: =IF($A6="","",IF(B6="Gold",GoldPrice,INDEX(TierPrices,MATCH(E6,TierQty,1),MATCH(B6,TierSpecs,0)))) | H6: =IF($A6="","",C6*D6) | I6: =IF($A6="","",E6*G6) | J6: =IF($A6="","",I6*WageCoef) | K6: 0 | L6: =IF($A6="","",H6-I6-J6-N(K6)) | M6: =IF(OR($A6="",N(H6)=0),"",L6/H6) | N6: =IF(OR($A6="",N(C6)=0),"",(E6*G6*(1+WageCoef)+N(K6))/C6) | O6: =IF(OR($A6="",N6=""),"",D6-N6)
A7: C09 | B7: Copper | C7: 40 | D7: 6500 | E7: =IF($A7="","",ROUNDUP(C7/(1-RejRate),0)) | F7: =IF($A7="","",E7-C7) | G7: =IF($A7="","",IF(B7="Gold",GoldPrice,INDEX(TierPrices,MATCH(E7,TierQty,1),MATCH(B7,TierSpecs,0)))) | H7: =IF($A7="","",C7*D7) | I7: =IF($A7="","",E7*G7) | J7: =IF($A7="","",I7*WageCoef) | K7: 0 | L7: =IF($A7="","",H7-I7-J7-N(K7)) | M7: =IF(OR($A7="",N(H7)=0),"",L7/H7) | N7: =IF(OR($A7="",N(C7)=0),"",(E7*G7*(1+WageCoef)+N(K7))/C7) | O7: =IF(OR($A7="",N7=""),"",D7-N7)
E8: =IF($A8="","",ROUNDUP(C8/(1-RejRate),0)) | F8: =IF($A8="","",E8-C8) | G8: =IF($A8="","",IF(B8="Gold",GoldPrice,INDEX(TierPrices,MATCH(E8,TierQty,1),MATCH(B8,TierSpecs,0)))) | H8: =IF($A8="","",C8*D8) | I8: =IF($A8="","",E8*G8) | J8: =IF($A8="","",I8*WageCoef) | L8: =IF($A8="","",H8-I8-J8-N(K8)) | M8: =IF(OR($A8="",N(H8)=0),"",L8/H8) | N8: =IF(OR($A8="",N(C8)=0),"",(E8*G8*(1+WageCoef)+N(K8))/C8) | O8: =IF(OR($A8="",N8=""),"",D8-N8)
E9: =IF($A9="","",ROUNDUP(C9/(1-RejRate),0)) | F9: =IF($A9="","",E9-C9) | G9: =IF($A9="","",IF(B9="Gold",GoldPrice,INDEX(TierPrices,MATCH(E9,TierQty,1),MATCH(B9,TierSpecs,0)))) | H9: =IF($A9="","",C9*D9) | I9: =IF($A9="","",E9*G9) | J9: =IF($A9="","",I9*WageCoef) | L9: =IF($A9="","",H9-I9-J9-N(K9)) | M9: =IF(OR($A9="",N(H9)=0),"",L9/H9) | N9: =IF(OR($A9="",N(C9)=0),"",(E9*G9*(1+WageCoef)+N(K9))/C9) | O9: =IF(OR($A9="",N9=""),"",D9-N9)
E10: =IF($A10="","",ROUNDUP(C10/(1-RejRate),0)) | F10: =IF($A10="","",E10-C10) | G10: =IF($A10="","",IF(B10="Gold",GoldPrice,INDEX(TierPrices,MATCH(E10,TierQty,1),MATCH(B10,TierSpecs,0)))) | H10: =IF($A10="","",C10*D10) | I10: =IF($A10="","",E10*G10) | J10: =IF($A10="","",I10*WageCoef) | L10: =IF($A10="","",H10-I10-J10-N(K10)) | M10: =IF(OR($A10="",N(H10)=0),"",L10/H10) | N10: =IF(OR($A10="",N(C10)=0),"",(E10*G10*(1+WageCoef)+N(K10))/C10) | O10: =IF(OR($A10="",N10=""),"",D10-N10)
E11: =IF($A11="","",ROUNDUP(C11/(1-RejRate),0)) | F11: =IF($A11="","",E11-C11) | G11: =IF($A11="","",IF(B11="Gold",GoldPrice,INDEX(TierPrices,MATCH(E11,TierQty,1),MATCH(B11,TierSpecs,0)))) | H11: =IF($A11="","",C11*D11) | I11: =IF($A11="","",E11*G11) | J11: =IF($A11="","",I11*WageCoef) | L11: =IF($A11="","",H11-I11-J11-N(K11)) | M11: =IF(OR($A11="",N(H11)=0),"",L11/H11) | N11: =IF(OR($A11="",N(C11)=0),"",(E11*G11*(1+WageCoef)+N(K11))/C11) | O11: =IF(OR($A11="",N11=""),"",D11-N11)
E12: =IF($A12="","",ROUNDUP(C12/(1-RejRate),0)) | F12: =IF($A12="","",E12-C12) | G12: =IF($A12="","",IF(B12="Gold",GoldPrice,INDEX(TierPrices,MATCH(E12,TierQty,1),MATCH(B12,TierSpecs,0)))) | H12: =IF($A12="","",C12*D12) | I12: =IF($A12="","",E12*G12) | J12: =IF($A12="","",I12*WageCoef) | L12: =IF($A12="","",H12-I12-J12-N(K12)) | M12: =IF(OR($A12="",N(H12)=0),"",L12/H12) | N12: =IF(OR($A12="",N(C12)=0),"",(E12*G12*(1+WageCoef)+N(K12))/C12) | O12: =IF(OR($A12="",N12=""),"",D12-N12)
E13: =IF($A13="","",ROUNDUP(C13/(1-RejRate),0)) | F13: =IF($A13="","",E13-C13) | G13: =IF($A13="","",IF(B13="Gold",GoldPrice,INDEX(TierPrices,MATCH(E13,TierQty,1),MATCH(B13,TierSpecs,0)))) | H13: =IF($A13="","",C13*D13) | I13: =IF($A13="","",E13*G13) | J13: =IF($A13="","",I13*WageCoef) | L13: =IF($A13="","",H13-I13-J13-N(K13)) | M13: =IF(OR($A13="",N(H13)=0),"",L13/H13) | N13: =IF(OR($A13="",N(C13)=0),"",(E13*G13*(1+WageCoef)+N(K13))/C13) | O13: =IF(OR($A13="",N13=""),"",D13-N13)
E14: =IF($A14="","",ROUNDUP(C14/(1-RejRate),0)) | F14: =IF($A14="","",E14-C14) | G14: =IF($A14="","",IF(B14="Gold",GoldPrice,INDEX(TierPrices,MATCH(E14,TierQty,1),MATCH(B14,TierSpecs,0)))) | H14: =IF($A14="","",C14*D14) | I14: =IF($A14="","",E14*G14) | J14: =IF($A14="","",I14*WageCoef) | L14: =IF($A14="","",H14-I14-J14-N(K14)) | M14: =IF(OR($A14="",N(H14)=0),"",L14/H14) | N14: =IF(OR($A14="",N(C14)=0),"",(E14*G14*(1+WageCoef)+N(K14))/C14) | O14: =IF(OR($A14="",N14=""),"",D14-N14)
E15: =IF($A15="","",ROUNDUP(C15/(1-RejRate),0)) | F15: =IF($A15="","",E15-C15) | G15: =IF($A15="","",IF(B15="Gold",GoldPrice,INDEX(TierPrices,MATCH(E15,TierQty,1),MATCH(B15,TierSpecs,0)))) | H15: =IF($A15="","",C15*D15) | I15: =IF($A15="","",E15*G15) | J15: =IF($A15="","",I15*WageCoef) | L15: =IF($A15="","",H15-I15-J15-N(K15)) | M15: =IF(OR($A15="",N(H15)=0),"",L15/H15) | N15: =IF(OR($A15="",N(C15)=0),"",(E15*G15*(1+WageCoef)+N(K15))/C15) | O15: =IF(OR($A15="",N15=""),"",D15-N15)
E16: =IF($A16="","",ROUNDUP(C16/(1-RejRate),0)) | F16: =IF($A16="","",E16-C16) | G16: =IF($A16="","",IF(B16="Gold",GoldPrice,INDEX(TierPrices,MATCH(E16,TierQty,1),MATCH(B16,TierSpecs,0)))) | H16: =IF($A16="","",C16*D16) | I16: =IF($A16="","",E16*G16) | J16: =IF($A16="","",I16*WageCoef) | L16: =IF($A16="","",H16-I16-J16-N(K16)) | M16: =IF(OR($A16="",N(H16)=0),"",L16/H16) | N16: =IF(OR($A16="",N(C16)=0),"",(E16*G16*(1+WageCoef)+N(K16))/C16) | O16: =IF(OR($A16="",N16=""),"",D16-N16)
E17: =IF($A17="","",ROUNDUP(C17/(1-RejRate),0)) | F17: =IF($A17="","",E17-C17) | G17: =IF($A17="","",IF(B17="Gold",GoldPrice,INDEX(TierPrices,MATCH(E17,TierQty,1),MATCH(B17,TierSpecs,0)))) | H17: =IF($A17="","",C17*D17) | I17: =IF($A17="","",E17*G17) | J17: =IF($A17="","",I17*WageCoef) | L17: =IF($A17="","",H17-I17-J17-N(K17)) | M17: =IF(OR($A17="",N(H17)=0),"",L17/H17) | N17: =IF(OR($A17="",N(C17)=0),"",(E17*G17*(1+WageCoef)+N(K17))/C17) | O17: =IF(OR($A17="",N17=""),"",D17-N17)
E18: =IF($A18="","",ROUNDUP(C18/(1-RejRate),0)) | F18: =IF($A18="","",E18-C18) | G18: =IF($A18="","",IF(B18="Gold",GoldPrice,INDEX(TierPrices,MATCH(E18,TierQty,1),MATCH(B18,TierSpecs,0)))) | H18: =IF($A18="","",C18*D18) | I18: =IF($A18="","",E18*G18) | J18: =IF($A18="","",I18*WageCoef) | L18: =IF($A18="","",H18-I18-J18-N(K18)) | M18: =IF(OR($A18="",N(H18)=0),"",L18/H18) | N18: =IF(OR($A18="",N(C18)=0),"",(E18*G18*(1+WageCoef)+N(K18))/C18) | O18: =IF(OR($A18="",N18=""),"",D18-N18)
E19: =IF($A19="","",ROUNDUP(C19/(1-RejRate),0)) | F19: =IF($A19="","",E19-C19) | G19: =IF($A19="","",IF(B19="Gold",GoldPrice,INDEX(TierPrices,MATCH(E19,TierQty,1),MATCH(B19,TierSpecs,0)))) | H19: =IF($A19="","",C19*D19) | I19: =IF($A19="","",E19*G19) | J19: =IF($A19="","",I19*WageCoef) | L19: =IF($A19="","",H19-I19-J19-N(K19)) | M19: =IF(OR($A19="",N(H19)=0),"",L19/H19) | N19: =IF(OR($A19="",N(C19)=0),"",(E19*G19*(1+WageCoef)+N(K19))/C19) | O19: =IF(OR($A19="",N19=""),"",D19-N19)
... E34: =IF($A34="","",ROUNDUP(C34/(1-RejRate),0)) | F34: =IF($A34="","",E34-C34) | G34: =IF($A34="","",IF(B34="Gold",GoldPrice,INDEX(TierPrices,MATCH(E34,TierQty,1),MATCH(B34,TierSpecs,0)))) | H34: =IF($A34="","",C34*D34) | I34: =IF($A34="","",E34*G34) | J34: =IF($A34="","",I34*WageCoef) | L34: =IF($A34="","",H34-I34-J34-N(K34)) | M34: =IF(OR($A34="",N(H34)=0),"",L34/H34) | N34: =IF(OR($A34="",N(C34)=0),"",(E34*G34*(1+WageCoef)+N(K34))/C34) | O34: =IF(OR($A34="",N34=""),"",D34-N34)
A36: Total | C36: =SUM(C5:C34) | E36: =SUM(E5:E34) | F36: =SUM(F5:F34) | H36: =SUM(H5:H34) | I36: =SUM(I5:I34) | J36: =SUM(J5:J34) | K36: =SUM(K5:K34) | L36: =SUM(L5:L34) | M36: =IF(N(H36)=0,"",L36/H36)

Sheet P&L Y1
A1: Year 1 profit and loss
A2: Contract columns read Contracts Y1 row by row; blank columns are unused contract rows. Year total sums the whole contract range. Costs shown as positive amounts that are subtracted.
A4: Contract | B4: Year total | C4: =IF('Contracts Y1'!$A5="","",'Contracts Y1'!$A5) | D4: =IF('Contracts Y1'!$A6="","",'Contracts Y1'!$A6) | E4: =IF('Contracts Y1'!$A7="","",'Contracts Y1'!$A7) | F4: =IF('Contracts Y1'!$A8="","",'Contracts Y1'!$A8) | G4: =IF('Contracts Y1'!$A9="","",'Contracts Y1'!$A9) | H4: =IF('Contracts Y1'!$A10="","",'Contracts Y1'!$A10) | I4: =IF('Contracts Y1'!$A11="","",'Contracts Y1'!$A11) | J4: =IF('Contracts Y1'!$A12="","",'Contracts Y1'!$A12) | K4: =IF('Contracts Y1'!$A13="","",'Contracts Y1'!$A13) | L4: =IF('Contracts Y1'!$A14="","",'Contracts Y1'!$A14) | M4: =IF('Contracts Y1'!$A15="","",'Contracts Y1'!$A15) | N4: =IF('Contracts Y1'!$A16="","",'Contracts Y1'!$A16) | O4: =IF('Contracts Y1'!$A17="","",'Contracts Y1'!$A17) | P4: =IF('Contracts Y1'!$A18="","",'Contracts Y1'!$A18) | Q4: =IF('Contracts Y1'!$A19="","",'Contracts Y1'!$A19) | R4: =IF('Contracts Y1'!$A20="","",'Contracts Y1'!$A20) | S4: =IF('Contracts Y1'!$A21="","",'Contracts Y1'!$A21) | T4: =IF('Contracts Y1'!$A22="","",'Contracts Y1'!$A22) | U4: =IF('Contracts Y1'!$A23="","",'Contracts Y1'!$A23) | V4: =IF('Contracts Y1'!$A24="","",'Contracts Y1'!$A24) | W4: =IF('Contracts Y1'!$A25="","",'Contracts Y1'!$A25) | X4: =IF('Contracts Y1'!$A26="","",'Contracts Y1'!$A26) | Y4: =IF('Contracts Y1'!$A27="","",'Contracts Y1'!$A27) | Z4: =IF('Contracts Y1'!$A28="","",'Contracts Y1'!$A28) | AA4: =IF('Contracts Y1'!$A29="","",'Contracts Y1'!$A29) | AB4: =IF('Contracts Y1'!$A30="","",'Contracts Y1'!$A30) | AC4: =IF('Contracts Y1'!$A31="","",'Contracts Y1'!$A31) | AD4: =IF('Contracts Y1'!$A32="","",'Contracts Y1'!$A32) | AE4: =IF('Contracts Y1'!$A33="","",'Contracts Y1'!$A33) | AF4: =IF('Contracts Y1'!$A34="","",'Contracts Y1'!$A34)
A5: Spec | C5: =IF('Contracts Y1'!$A5="","",'Contracts Y1'!$B5) | D5: =IF('Contracts Y1'!$A6="","",'Contracts Y1'!$B6) | E5: =IF('Contracts Y1'!$A7="","",'Contracts Y1'!$B7) | F5: =IF('Contracts Y1'!$A8="","",'Contracts Y1'!$B8) | G5: =IF('Contracts Y1'!$A9="","",'Contracts Y1'!$B9) | H5: =IF('Contracts Y1'!$A10="","",'Contracts Y1'!$B10) | I5: =IF('Contracts Y1'!$A11="","",'Contracts Y1'!$B11) | J5: =IF('Contracts Y1'!$A12="","",'Contracts Y1'!$B12) | K5: =IF('Contracts Y1'!$A13="","",'Contracts Y1'!$B13) | L5: =IF('Contracts Y1'!$A14="","",'Contracts Y1'!$B14) | M5: =IF('Contracts Y1'!$A15="","",'Contracts Y1'!$B15) | N5: =IF('Contracts Y1'!$A16="","",'Contracts Y1'!$B16) | O5: =IF('Contracts Y1'!$A17="","",'Contracts Y1'!$B17) | P5: =IF('Contracts Y1'!$A18="","",'Contracts Y1'!$B18) | Q5: =IF('Contracts Y1'!$A19="","",'Contracts Y1'!$B19) | R5: =IF('Contracts Y1'!$A20="","",'Contracts Y1'!$B20) | S5: =IF('Contracts Y1'!$A21="","",'Contracts Y1'!$B21) | T5: =IF('Contracts Y1'!$A22="","",'Contracts Y1'!$B22) | U5: =IF('Contracts Y1'!$A23="","",'Contracts Y1'!$B23) | V5: =IF('Contracts Y1'!$A24="","",'Contracts Y1'!$B24) | W5: =IF('Contracts Y1'!$A25="","",'Contracts Y1'!$B25) | X5: =IF('Contracts Y1'!$A26="","",'Contracts Y1'!$B26) | Y5: =IF('Contracts Y1'!$A27="","",'Contracts Y1'!$B27) | Z5: =IF('Contracts Y1'!$A28="","",'Contracts Y1'!$B28) | AA5: =IF('Contracts Y1'!$A29="","",'Contracts Y1'!$B29) | AB5: =IF('Contracts Y1'!$A30="","",'Contracts Y1'!$B30) | AC5: =IF('Contracts Y1'!$A31="","",'Contracts Y1'!$B31) | AD5: =IF('Contracts Y1'!$A32="","",'Contracts Y1'!$B32) | AE5: =IF('Contracts Y1'!$A33="","",'Contracts Y1'!$B33) | AF5: =IF('Contracts Y1'!$A34="","",'Contracts Y1'!$B34)
A6: Contract revenue | B6: =SUM('Contracts Y1'!H$5:H$34) | C6: =IF(C$4="","",'Contracts Y1'!H5) | D6: =IF(D$4="","",'Contracts Y1'!H6) | E6: =IF(E$4="","",'Contracts Y1'!H7) | F6: =IF(F$4="","",'Contracts Y1'!H8) | G6: =IF(G$4="","",'Contracts Y1'!H9) | H6: =IF(H$4="","",'Contracts Y1'!H10) | I6: =IF(I$4="","",'Contracts Y1'!H11) | J6: =IF(J$4="","",'Contracts Y1'!H12) | K6: =IF(K$4="","",'Contracts Y1'!H13) | L6: =IF(L$4="","",'Contracts Y1'!H14) | M6: =IF(M$4="","",'Contracts Y1'!H15) | N6: =IF(N$4="","",'Contracts Y1'!H16) | O6: =IF(O$4="","",'Contracts Y1'!H17) | P6: =IF(P$4="","",'Contracts Y1'!H18) | Q6: =IF(Q$4="","",'Contracts Y1'!H19) | R6: =IF(R$4="","",'Contracts Y1'!H20) | S6: =IF(S$4="","",'Contracts Y1'!H21) | T6: =IF(T$4="","",'Contracts Y1'!H22) | U6: =IF(U$4="","",'Contracts Y1'!H23) | V6: =IF(V$4="","",'Contracts Y1'!H24) | W6: =IF(W$4="","",'Contracts Y1'!H25) | X6: =IF(X$4="","",'Contracts Y1'!H26) | Y6: =IF(Y$4="","",'Contracts Y1'!H27) | Z6: =IF(Z$4="","",'Contracts Y1'!H28) | AA6: =IF(AA$4="","",'Contracts Y1'!H29) | AB6: =IF(AB$4="","",'Contracts Y1'!H30) | AC6: =IF(AC$4="","",'Contracts Y1'!H31) | AD6: =IF(AD$4="","",'Contracts Y1'!H32) | AE6: =IF(AE$4="","",'Contracts Y1'!H33) | AF6: =IF(AF$4="","",'Contracts Y1'!H34)
A7: Less raw materials used | B7: =SUM('Contracts Y1'!I$5:I$34) | C7: =IF(C$4="","",'Contracts Y1'!I5) | D7: =IF(D$4="","",'Contracts Y1'!I6) | E7: =IF(E$4="","",'Contracts Y1'!I7) | F7: =IF(F$4="","",'Contracts Y1'!I8) | G7: =IF(G$4="","",'Contracts Y1'!I9) | H7: =IF(H$4="","",'Contracts Y1'!I10) | I7: =IF(I$4="","",'Contracts Y1'!I11) | J7: =IF(J$4="","",'Contracts Y1'!I12) | K7: =IF(K$4="","",'Contracts Y1'!I13) | L7: =IF(L$4="","",'Contracts Y1'!I14) | M7: =IF(M$4="","",'Contracts Y1'!I15) | N7: =IF(N$4="","",'Contracts Y1'!I16) | O7: =IF(O$4="","",'Contracts Y1'!I17) | P7: =IF(P$4="","",'Contracts Y1'!I18) | Q7: =IF(Q$4="","",'Contracts Y1'!I19) | R7: =IF(R$4="","",'Contracts Y1'!I20) | S7: =IF(S$4="","",'Contracts Y1'!I21) | T7: =IF(T$4="","",'Contracts Y1'!I22) | U7: =IF(U$4="","",'Contracts Y1'!I23) | V7: =IF(V$4="","",'Contracts Y1'!I24) | W7: =IF(W$4="","",'Contracts Y1'!I25) | X7: =IF(X$4="","",'Contracts Y1'!I26) | Y7: =IF(Y$4="","",'Contracts Y1'!I27) | Z7: =IF(Z$4="","",'Contracts Y1'!I28) | AA7: =IF(AA$4="","",'Contracts Y1'!I29) | AB7: =IF(AB$4="","",'Contracts Y1'!I30) | AC7: =IF(AC$4="","",'Contracts Y1'!I31) | AD7: =IF(AD$4="","",'Contracts Y1'!I32) | AE7: =IF(AE$4="","",'Contracts Y1'!I33) | AF7: =IF(AF$4="","",'Contracts Y1'!I34)
A8: Less production wages | B8: =SUM('Contracts Y1'!J$5:J$34) | C8: =IF(C$4="","",'Contracts Y1'!J5) | D8: =IF(D$4="","",'Contracts Y1'!J6) | E8: =IF(E$4="","",'Contracts Y1'!J7) | F8: =IF(F$4="","",'Contracts Y1'!J8) | G8: =IF(G$4="","",'Contracts Y1'!J9) | H8: =IF(H$4="","",'Contracts Y1'!J10) | I8: =IF(I$4="","",'Contracts Y1'!J11) | J8: =IF(J$4="","",'Contracts Y1'!J12) | K8: =IF(K$4="","",'Contracts Y1'!J13) | L8: =IF(L$4="","",'Contracts Y1'!J14) | M8: =IF(M$4="","",'Contracts Y1'!J15) | N8: =IF(N$4="","",'Contracts Y1'!J16) | O8: =IF(O$4="","",'Contracts Y1'!J17) | P8: =IF(P$4="","",'Contracts Y1'!J18) | Q8: =IF(Q$4="","",'Contracts Y1'!J19) | R8: =IF(R$4="","",'Contracts Y1'!J20) | S8: =IF(S$4="","",'Contracts Y1'!J21) | T8: =IF(T$4="","",'Contracts Y1'!J22) | U8: =IF(U$4="","",'Contracts Y1'!J23) | V8: =IF(V$4="","",'Contracts Y1'!J24) | W8: =IF(W$4="","",'Contracts Y1'!J25) | X8: =IF(X$4="","",'Contracts Y1'!J26) | Y8: =IF(Y$4="","",'Contracts Y1'!J27) | Z8: =IF(Z$4="","",'Contracts Y1'!J28) | AA8: =IF(AA$4="","",'Contracts Y1'!J29) | AB8: =IF(AB$4="","",'Contracts Y1'!J30) | AC8: =IF(AC$4="","",'Contracts Y1'!J31) | AD8: =IF(AD$4="","",'Contracts Y1'!J32) | AE8: =IF(AE$4="","",'Contracts Y1'!J33) | AF8: =IF(AF$4="","",'Contracts Y1'!J34)
A9: Less other direct contract expenses | B9: =SUM('Contracts Y1'!K$5:K$34) | C9: =IF(C$4="","",N('Contracts Y1'!K5)) | D9: =IF(D$4="","",N('Contracts Y1'!K6)) | E9: =IF(E$4="","",N('Contracts Y1'!K7)) | F9: =IF(F$4="","",N('Contracts Y1'!K8)) | G9: =IF(G$4="","",N('Contracts Y1'!K9)) | H9: =IF(H$4="","",N('Contracts Y1'!K10)) | I9: =IF(I$4="","",N('Contracts Y1'!K11)) | J9: =IF(J$4="","",N('Contracts Y1'!K12)) | K9: =IF(K$4="","",N('Contracts Y1'!K13)) | L9: =IF(L$4="","",N('Contracts Y1'!K14)) | M9: =IF(M$4="","",N('Contracts Y1'!K15)) | N9: =IF(N$4="","",N('Contracts Y1'!K16)) | O9: =IF(O$4="","",N('Contracts Y1'!K17)) | P9: =IF(P$4="","",N('Contracts Y1'!K18)) | Q9: =IF(Q$4="","",N('Contracts Y1'!K19)) | R9: =IF(R$4="","",N('Contracts Y1'!K20)) | S9: =IF(S$4="","",N('Contracts Y1'!K21)) | T9: =IF(T$4="","",N('Contracts Y1'!K22)) | U9: =IF(U$4="","",N('Contracts Y1'!K23)) | V9: =IF(V$4="","",N('Contracts Y1'!K24)) | W9: =IF(W$4="","",N('Contracts Y1'!K25)) | X9: =IF(X$4="","",N('Contracts Y1'!K26)) | Y9: =IF(Y$4="","",N('Contracts Y1'!K27)) | Z9: =IF(Z$4="","",N('Contracts Y1'!K28)) | AA9: =IF(AA$4="","",N('Contracts Y1'!K29)) | AB9: =IF(AB$4="","",N('Contracts Y1'!K30)) | AC9: =IF(AC$4="","",N('Contracts Y1'!K31)) | AD9: =IF(AD$4="","",N('Contracts Y1'!K32)) | AE9: =IF(AE$4="","",N('Contracts Y1'!K33)) | AF9: =IF(AF$4="","",N('Contracts Y1'!K34))
A10: Contribution margin | B10: =B6-B7-B8-B9 | C10: =IF(C$4="","",C6-C7-C8-C9) | D10: =IF(D$4="","",D6-D7-D8-D9) | E10: =IF(E$4="","",E6-E7-E8-E9) | F10: =IF(F$4="","",F6-F7-F8-F9) | G10: =IF(G$4="","",G6-G7-G8-G9) | H10: =IF(H$4="","",H6-H7-H8-H9) | I10: =IF(I$4="","",I6-I7-I8-I9) | J10: =IF(J$4="","",J6-J7-J8-J9) | ... AF10: =IF(AF$4="","",AF6-AF7-AF8-AF9)
A11: Less fixed operating expenses | B11: =FixedTotal
A12: Operating profit | B12: =B10-B11
A13: CM % | B13: =IF(B6=0,"",B10/B6) | C13: =IF(N(C6)=0,"",C10/C6) | D13: =IF(N(D6)=0,"",D10/D6) | E13: =IF(N(E6)=0,"",E10/E6) | F13: =IF(N(F6)=0,"",F10/F6) | G13: =IF(N(G6)=0,"",G10/G6) | H13: =IF(N(H6)=0,"",H10/H6) | I13: =IF(N(I6)=0,"",I10/I6) | J13: =IF(N(J6)=0,"",J10/J6) | ... AF13: =IF(N(AF6)=0,"",AF10/AF6)
A14: Operating margin % | B14: =IF(B6=0,"",B12/B6)
A15: Share of market (revenue / market size) | B15: =IF(N(Inputs!$B$31)=0,"",B6/Inputs!$B$31) | C15: =IF(OR(C$4="",N(Inputs!$B$31)=0),"",C6/Inputs!$B$31) | D15: =IF(OR(D$4="",N(Inputs!$B$31)=0),"",D6/Inputs!$B$31) | E15: =IF(OR(E$4="",N(Inputs!$B$31)=0),"",E6/Inputs!$B$31) | F15: =IF(OR(F$4="",N(Inputs!$B$31)=0),"",F6/Inputs!$B$31) | G15: =IF(OR(G$4="",N(Inputs!$B$31)=0),"",G6/Inputs!$B$31) | H15: =IF(OR(H$4="",N(Inputs!$B$31)=0),"",H6/Inputs!$B$31) | I15: =IF(OR(I$4="",N(Inputs!$B$31)=0),"",I6/Inputs!$B$31) | J15: =IF(OR(J$4="",N(Inputs!$B$31)=0),"",J6/Inputs!$B$31) | ... AF15: =IF(OR(AF$4="",N(Inputs!$B$31)=0),"",AF6/Inputs!$B$31)
A17: Fixed expenses, operating profit and operating margin are reported for the year only, not per contract.

Sheet Contracts Y2
A1: Year 2 contracts won
A2: Type Contract ID, Spec, Accepted qty and Price (blue cells) in any empty row; every other column calculates. Each contract is its own purchase order.
A3: Orange price = outside the case price range (Inputs B8:B9). Other direct defaults to 0.
A4: Contract ID | B4: Spec | C4: Accepted qty (BB) | D4: Price per BB ($) | E4: Production qty (BB) | F4: Rejected qty (BB) | G4: RM price per BB ($) | H4: Revenue ($) | I4: Raw materials ($) | J4: Wages ($) | K4: Other direct ($) | L4: Contribution margin ($) | M4: CM % | N4: Break-even price per accepted BB ($) | O4: Price vs break-even ($)
E5: =IF($A5="","",ROUNDUP(C5/(1-RejRate),0)) | F5: =IF($A5="","",E5-C5) | G5: =IF($A5="","",IF(B5="Gold",GoldPrice,INDEX(TierPrices,MATCH(E5,TierQty,1),MATCH(B5,TierSpecs,0)))) | H5: =IF($A5="","",C5*D5) | I5: =IF($A5="","",E5*G5) | J5: =IF($A5="","",I5*WageCoef) | L5: =IF($A5="","",H5-I5-J5-N(K5)) | M5: =IF(OR($A5="",N(H5)=0),"",L5/H5) | N5: =IF(OR($A5="",N(C5)=0),"",(E5*G5*(1+WageCoef)+N(K5))/C5) | O5: =IF(OR($A5="",N5=""),"",D5-N5)
E6: =IF($A6="","",ROUNDUP(C6/(1-RejRate),0)) | F6: =IF($A6="","",E6-C6) | G6: =IF($A6="","",IF(B6="Gold",GoldPrice,INDEX(TierPrices,MATCH(E6,TierQty,1),MATCH(B6,TierSpecs,0)))) | H6: =IF($A6="","",C6*D6) | I6: =IF($A6="","",E6*G6) | J6: =IF($A6="","",I6*WageCoef) | L6: =IF($A6="","",H6-I6-J6-N(K6)) | M6: =IF(OR($A6="",N(H6)=0),"",L6/H6) | N6: =IF(OR($A6="",N(C6)=0),"",(E6*G6*(1+WageCoef)+N(K6))/C6) | O6: =IF(OR($A6="",N6=""),"",D6-N6)
E7: =IF($A7="","",ROUNDUP(C7/(1-RejRate),0)) | F7: =IF($A7="","",E7-C7) | G7: =IF($A7="","",IF(B7="Gold",GoldPrice,INDEX(TierPrices,MATCH(E7,TierQty,1),MATCH(B7,TierSpecs,0)))) | H7: =IF($A7="","",C7*D7) | I7: =IF($A7="","",E7*G7) | J7: =IF($A7="","",I7*WageCoef) | L7: =IF($A7="","",H7-I7-J7-N(K7)) | M7: =IF(OR($A7="",N(H7)=0),"",L7/H7) | N7: =IF(OR($A7="",N(C7)=0),"",(E7*G7*(1+WageCoef)+N(K7))/C7) | O7: =IF(OR($A7="",N7=""),"",D7-N7)
E8: =IF($A8="","",ROUNDUP(C8/(1-RejRate),0)) | F8: =IF($A8="","",E8-C8) | G8: =IF($A8="","",IF(B8="Gold",GoldPrice,INDEX(TierPrices,MATCH(E8,TierQty,1),MATCH(B8,TierSpecs,0)))) | H8: =IF($A8="","",C8*D8) | I8: =IF($A8="","",E8*G8) | J8: =IF($A8="","",I8*WageCoef) | L8: =IF($A8="","",H8-I8-J8-N(K8)) | M8: =IF(OR($A8="",N(H8)=0),"",L8/H8) | N8: =IF(OR($A8="",N(C8)=0),"",(E8*G8*(1+WageCoef)+N(K8))/C8) | O8: =IF(OR($A8="",N8=""),"",D8-N8)
E9: =IF($A9="","",ROUNDUP(C9/(1-RejRate),0)) | F9: =IF($A9="","",E9-C9) | G9: =IF($A9="","",IF(B9="Gold",GoldPrice,INDEX(TierPrices,MATCH(E9,TierQty,1),MATCH(B9,TierSpecs,0)))) | H9: =IF($A9="","",C9*D9) | I9: =IF($A9="","",E9*G9) | J9: =IF($A9="","",I9*WageCoef) | L9: =IF($A9="","",H9-I9-J9-N(K9)) | M9: =IF(OR($A9="",N(H9)=0),"",L9/H9) | N9: =IF(OR($A9="",N(C9)=0),"",(E9*G9*(1+WageCoef)+N(K9))/C9) | O9: =IF(OR($A9="",N9=""),"",D9-N9)
E10: =IF($A10="","",ROUNDUP(C10/(1-RejRate),0)) | F10: =IF($A10="","",E10-C10) | G10: =IF($A10="","",IF(B10="Gold",GoldPrice,INDEX(TierPrices,MATCH(E10,TierQty,1),MATCH(B10,TierSpecs,0)))) | H10: =IF($A10="","",C10*D10) | I10: =IF($A10="","",E10*G10) | J10: =IF($A10="","",I10*WageCoef) | L10: =IF($A10="","",H10-I10-J10-N(K10)) | M10: =IF(OR($A10="",N(H10)=0),"",L10/H10) | N10: =IF(OR($A10="",N(C10)=0),"",(E10*G10*(1+WageCoef)+N(K10))/C10) | O10: =IF(OR($A10="",N10=""),"",D10-N10)
E11: =IF($A11="","",ROUNDUP(C11/(1-RejRate),0)) | F11: =IF($A11="","",E11-C11) | G11: =IF($A11="","",IF(B11="Gold",GoldPrice,INDEX(TierPrices,MATCH(E11,TierQty,1),MATCH(B11,TierSpecs,0)))) | H11: =IF($A11="","",C11*D11) | I11: =IF($A11="","",E11*G11) | J11: =IF($A11="","",I11*WageCoef) | L11: =IF($A11="","",H11-I11-J11-N(K11)) | M11: =IF(OR($A11="",N(H11)=0),"",L11/H11) | N11: =IF(OR($A11="",N(C11)=0),"",(E11*G11*(1+WageCoef)+N(K11))/C11) | O11: =IF(OR($A11="",N11=""),"",D11-N11)
E12: =IF($A12="","",ROUNDUP(C12/(1-RejRate),0)) | F12: =IF($A12="","",E12-C12) | G12: =IF($A12="","",IF(B12="Gold",GoldPrice,INDEX(TierPrices,MATCH(E12,TierQty,1),MATCH(B12,TierSpecs,0)))) | H12: =IF($A12="","",C12*D12) | I12: =IF($A12="","",E12*G12) | J12: =IF($A12="","",I12*WageCoef) | L12: =IF($A12="","",H12-I12-J12-N(K12)) | M12: =IF(OR($A12="",N(H12)=0),"",L12/H12) | N12: =IF(OR($A12="",N(C12)=0),"",(E12*G12*(1+WageCoef)+N(K12))/C12) | O12: =IF(OR($A12="",N12=""),"",D12-N12)
E13: =IF($A13="","",ROUNDUP(C13/(1-RejRate),0)) | F13: =IF($A13="","",E13-C13) | G13: =IF($A13="","",IF(B13="Gold",GoldPrice,INDEX(TierPrices,MATCH(E13,TierQty,1),MATCH(B13,TierSpecs,0)))) | H13: =IF($A13="","",C13*D13) | I13: =IF($A13="","",E13*G13) | J13: =IF($A13="","",I13*WageCoef) | L13: =IF($A13="","",H13-I13-J13-N(K13)) | M13: =IF(OR($A13="",N(H13)=0),"",L13/H13) | N13: =IF(OR($A13="",N(C13)=0),"",(E13*G13*(1+WageCoef)+N(K13))/C13) | O13: =IF(OR($A13="",N13=""),"",D13-N13)
E14: =IF($A14="","",ROUNDUP(C14/(1-RejRate),0)) | F14: =IF($A14="","",E14-C14) | G14: =IF($A14="","",IF(B14="Gold",GoldPrice,INDEX(TierPrices,MATCH(E14,TierQty,1),MATCH(B14,TierSpecs,0)))) | H14: =IF($A14="","",C14*D14) | I14: =IF($A14="","",E14*G14) | J14: =IF($A14="","",I14*WageCoef) | L14: =IF($A14="","",H14-I14-J14-N(K14)) | M14: =IF(OR($A14="",N(H14)=0),"",L14/H14) | N14: =IF(OR($A14="",N(C14)=0),"",(E14*G14*(1+WageCoef)+N(K14))/C14) | O14: =IF(OR($A14="",N14=""),"",D14-N14)
E15: =IF($A15="","",ROUNDUP(C15/(1-RejRate),0)) | F15: =IF($A15="","",E15-C15) | G15: =IF($A15="","",IF(B15="Gold",GoldPrice,INDEX(TierPrices,MATCH(E15,TierQty,1),MATCH(B15,TierSpecs,0)))) | H15: =IF($A15="","",C15*D15) | I15: =IF($A15="","",E15*G15) | J15: =IF($A15="","",I15*WageCoef) | L15: =IF($A15="","",H15-I15-J15-N(K15)) | M15: =IF(OR($A15="",N(H15)=0),"",L15/H15) | N15: =IF(OR($A15="",N(C15)=0),"",(E15*G15*(1+WageCoef)+N(K15))/C15) | O15: =IF(OR($A15="",N15=""),"",D15-N15)
E16: =IF($A16="","",ROUNDUP(C16/(1-RejRate),0)) | F16: =IF($A16="","",E16-C16) | G16: =IF($A16="","",IF(B16="Gold",GoldPrice,INDEX(TierPrices,MATCH(E16,TierQty,1),MATCH(B16,TierSpecs,0)))) | H16: =IF($A16="","",C16*D16) | I16: =IF($A16="","",E16*G16) | J16: =IF($A16="","",I16*WageCoef) | L16: =IF($A16="","",H16-I16-J16-N(K16)) | M16: =IF(OR($A16="",N(H16)=0),"",L16/H16) | N16: =IF(OR($A16="",N(C16)=0),"",(E16*G16*(1+WageCoef)+N(K16))/C16) | O16: =IF(OR($A16="",N16=""),"",D16-N16)
... E34: =IF($A34="","",ROUNDUP(C34/(1-RejRate),0)) | F34: =IF($A34="","",E34-C34) | G34: =IF($A34="","",IF(B34="Gold",GoldPrice,INDEX(TierPrices,MATCH(E34,TierQty,1),MATCH(B34,TierSpecs,0)))) | H34: =IF($A34="","",C34*D34) | I34: =IF($A34="","",E34*G34) | J34: =IF($A34="","",I34*WageCoef) | L34: =IF($A34="","",H34-I34-J34-N(K34)) | M34: =IF(OR($A34="",N(H34)=0),"",L34/H34) | N34: =IF(OR($A34="",N(C34)=0),"",(E34*G34*(1+WageCoef)+N(K34))/C34) | O34: =IF(OR($A34="",N34=""),"",D34-N34)
A36: Total | C36: =SUM(C5:C34) | E36: =SUM(E5:E34) | F36: =SUM(F5:F34) | H36: =SUM(H5:H34) | I36: =SUM(I5:I34) | J36: =SUM(J5:J34) | K36: =SUM(K5:K34) | L36: =SUM(L5:L34) | M36: =IF(N(H36)=0,"",L36/H36)

Sheet P&L Y2
A1: Year 2 profit and loss
A2: Contract columns read Contracts Y2 row by row; blank columns are unused contract rows. Year total sums the whole contract range. Costs shown as positive amounts that are subtracted.
A4: Contract | B4: Year total | C4: =IF('Contracts Y2'!$A5="","",'Contracts Y2'!$A5) | D4: =IF('Contracts Y2'!$A6="","",'Contracts Y2'!$A6) | E4: =IF('Contracts Y2'!$A7="","",'Contracts Y2'!$A7) | F4: =IF('Contracts Y2'!$A8="","",'Contracts Y2'!$A8) | G4: =IF('Contracts Y2'!$A9="","",'Contracts Y2'!$A9) | H4: =IF('Contracts Y2'!$A10="","",'Contracts Y2'!$A10) | I4: =IF('Contracts Y2'!$A11="","",'Contracts Y2'!$A11) | J4: =IF('Contracts Y2'!$A12="","",'Contracts Y2'!$A12) | K4: =IF('Contracts Y2'!$A13="","",'Contracts Y2'!$A13) | L4: =IF('Contracts Y2'!$A14="","",'Contracts Y2'!$A14) | M4: =IF('Contracts Y2'!$A15="","",'Contracts Y2'!$A15) | N4: =IF('Contracts Y2'!$A16="","",'Contracts Y2'!$A16) | O4: =IF('Contracts Y2'!$A17="","",'Contracts Y2'!$A17) | P4: =IF('Contracts Y2'!$A18="","",'Contracts Y2'!$A18) | Q4: =IF('Contracts Y2'!$A19="","",'Contracts Y2'!$A19) | R4: =IF('Contracts Y2'!$A20="","",'Contracts Y2'!$A20) | S4: =IF('Contracts Y2'!$A21="","",'Contracts Y2'!$A21) | T4: =IF('Contracts Y2'!$A22="","",'Contracts Y2'!$A22) | U4: =IF('Contracts Y2'!$A23="","",'Contracts Y2'!$A23) | V4: =IF('Contracts Y2'!$A24="","",'Contracts Y2'!$A24) | W4: =IF('Contracts Y2'!$A25="","",'Contracts Y2'!$A25) | X4: =IF('Contracts Y2'!$A26="","",'Contracts Y2'!$A26) | Y4: =IF('Contracts Y2'!$A27="","",'Contracts Y2'!$A27) | Z4: =IF('Contracts Y2'!$A28="","",'Contracts Y2'!$A28) | AA4: =IF('Contracts Y2'!$A29="","",'Contracts Y2'!$A29) | AB4: =IF('Contracts Y2'!$A30="","",'Contracts Y2'!$A30) | AC4: =IF('Contracts Y2'!$A31="","",'Contracts Y2'!$A31) | AD4: =IF('Contracts Y2'!$A32="","",'Contracts Y2'!$A32) | AE4: =IF('Contracts Y2'!$A33="","",'Contracts Y2'!$A33) | AF4: =IF('Contracts Y2'!$A34="","",'Contracts Y2'!$A34)
A5: Spec | C5: =IF('Contracts Y2'!$A5="","",'Contracts Y2'!$B5) | D5: =IF('Contracts Y2'!$A6="","",'Contracts Y2'!$B6) | E5: =IF('Contracts Y2'!$A7="","",'Contracts Y2'!$B7) | F5: =IF('Contracts Y2'!$A8="","",'Contracts Y2'!$B8) | G5: =IF('Contracts Y2'!$A9="","",'Contracts Y2'!$B9) | H5: =IF('Contracts Y2'!$A10="","",'Contracts Y2'!$B10) | I5: =IF('Contracts Y2'!$A11="","",'Contracts Y2'!$B11) | J5: =IF('Contracts Y2'!$A12="","",'Contracts Y2'!$B12) | K5: =IF('Contracts Y2'!$A13="","",'Contracts Y2'!$B13) | L5: =IF('Contracts Y2'!$A14="","",'Contracts Y2'!$B14) | M5: =IF('Contracts Y2'!$A15="","",'Contracts Y2'!$B15) | N5: =IF('Contracts Y2'!$A16="","",'Contracts Y2'!$B16) | O5: =IF('Contracts Y2'!$A17="","",'Contracts Y2'!$B17) | P5: =IF('Contracts Y2'!$A18="","",'Contracts Y2'!$B18) | Q5: =IF('Contracts Y2'!$A19="","",'Contracts Y2'!$B19) | R5: =IF('Contracts Y2'!$A20="","",'Contracts Y2'!$B20) | S5: =IF('Contracts Y2'!$A21="","",'Contracts Y2'!$B21) | T5: =IF('Contracts Y2'!$A22="","",'Contracts Y2'!$B22) | U5: =IF('Contracts Y2'!$A23="","",'Contracts Y2'!$B23) | V5: =IF('Contracts Y2'!$A24="","",'Contracts Y2'!$B24) | W5: =IF('Contracts Y2'!$A25="","",'Contracts Y2'!$B25) | X5: =IF('Contracts Y2'!$A26="","",'Contracts Y2'!$B26) | Y5: =IF('Contracts Y2'!$A27="","",'Contracts Y2'!$B27) | Z5: =IF('Contracts Y2'!$A28="","",'Contracts Y2'!$B28) | AA5: =IF('Contracts Y2'!$A29="","",'Contracts Y2'!$B29) | AB5: =IF('Contracts Y2'!$A30="","",'Contracts Y2'!$B30) | AC5: =IF('Contracts Y2'!$A31="","",'Contracts Y2'!$B31) | AD5: =IF('Contracts Y2'!$A32="","",'Contracts Y2'!$B32) | AE5: =IF('Contracts Y2'!$A33="","",'Contracts Y2'!$B33) | AF5: =IF('Contracts Y2'!$A34="","",'Contracts Y2'!$B34)
A6: Contract revenue | B6: =SUM('Contracts Y2'!H$5:H$34) | C6: =IF(C$4="","",'Contracts Y2'!H5) | D6: =IF(D$4="","",'Contracts Y2'!H6) | E6: =IF(E$4="","",'Contracts Y2'!H7) | F6: =IF(F$4="","",'Contracts Y2'!H8) | G6: =IF(G$4="","",'Contracts Y2'!H9) | H6: =IF(H$4="","",'Contracts Y2'!H10) | I6: =IF(I$4="","",'Contracts Y2'!H11) | J6: =IF(J$4="","",'Contracts Y2'!H12) | K6: =IF(K$4="","",'Contracts Y2'!H13) | L6: =IF(L$4="","",'Contracts Y2'!H14) | M6: =IF(M$4="","",'Contracts Y2'!H15) | N6: =IF(N$4="","",'Contracts Y2'!H16) | O6: =IF(O$4="","",'Contracts Y2'!H17) | P6: =IF(P$4="","",'Contracts Y2'!H18) | Q6: =IF(Q$4="","",'Contracts Y2'!H19) | R6: =IF(R$4="","",'Contracts Y2'!H20) | S6: =IF(S$4="","",'Contracts Y2'!H21) | T6: =IF(T$4="","",'Contracts Y2'!H22) | U6: =IF(U$4="","",'Contracts Y2'!H23) | V6: =IF(V$4="","",'Contracts Y2'!H24) | W6: =IF(W$4="","",'Contracts Y2'!H25) | X6: =IF(X$4="","",'Contracts Y2'!H26) | Y6: =IF(Y$4="","",'Contracts Y2'!H27) | Z6: =IF(Z$4="","",'Contracts Y2'!H28) | AA6: =IF(AA$4="","",'Contracts Y2'!H29) | AB6: =IF(AB$4="","",'Contracts Y2'!H30) | AC6: =IF(AC$4="","",'Contracts Y2'!H31) | AD6: =IF(AD$4="","",'Contracts Y2'!H32) | AE6: =IF(AE$4="","",'Contracts Y2'!H33) | AF6: =IF(AF$4="","",'Contracts Y2'!H34)
A7: Less raw materials used | B7: =SUM('Contracts Y2'!I$5:I$34) | C7: =IF(C$4="","",'Contracts Y2'!I5) | D7: =IF(D$4="","",'Contracts Y2'!I6) | E7: =IF(E$4="","",'Contracts Y2'!I7) | F7: =IF(F$4="","",'Contracts Y2'!I8) | G7: =IF(G$4="","",'Contracts Y2'!I9) | H7: =IF(H$4="","",'Contracts Y2'!I10) | I7: =IF(I$4="","",'Contracts Y2'!I11) | J7: =IF(J$4="","",'Contracts Y2'!I12) | K7: =IF(K$4="","",'Contracts Y2'!I13) | L7: =IF(L$4="","",'Contracts Y2'!I14) | M7: =IF(M$4="","",'Contracts Y2'!I15) | N7: =IF(N$4="","",'Contracts Y2'!I16) | O7: =IF(O$4="","",'Contracts Y2'!I17) | P7: =IF(P$4="","",'Contracts Y2'!I18) | Q7: =IF(Q$4="","",'Contracts Y2'!I19) | R7: =IF(R$4="","",'Contracts Y2'!I20) | S7: =IF(S$4="","",'Contracts Y2'!I21) | T7: =IF(T$4="","",'Contracts Y2'!I22) | U7: =IF(U$4="","",'Contracts Y2'!I23) | V7: =IF(V$4="","",'Contracts Y2'!I24) | W7: =IF(W$4="","",'Contracts Y2'!I25) | X7: =IF(X$4="","",'Contracts Y2'!I26) | Y7: =IF(Y$4="","",'Contracts Y2'!I27) | Z7: =IF(Z$4="","",'Contracts Y2'!I28) | AA7: =IF(AA$4="","",'Contracts Y2'!I29) | AB7: =IF(AB$4="","",'Contracts Y2'!I30) | AC7: =IF(AC$4="","",'Contracts Y2'!I31) | AD7: =IF(AD$4="","",'Contracts Y2'!I32) | AE7: =IF(AE$4="","",'Contracts Y2'!I33) | AF7: =IF(AF$4="","",'Contracts Y2'!I34)
A8: Less production wages | B8: =SUM('Contracts Y2'!J$5:J$34) | C8: =IF(C$4="","",'Contracts Y2'!J5) | D8: =IF(D$4="","",'Contracts Y2'!J6) | E8: =IF(E$4="","",'Contracts Y2'!J7) | F8: =IF(F$4="","",'Contracts Y2'!J8) | G8: =IF(G$4="","",'Contracts Y2'!J9) | H8: =IF(H$4="","",'Contracts Y2'!J10) | I8: =IF(I$4="","",'Contracts Y2'!J11) | J8: =IF(J$4="","",'Contracts Y2'!J12) | K8: =IF(K$4="","",'Contracts Y2'!J13) | L8: =IF(L$4="","",'Contracts Y2'!J14) | M8: =IF(M$4="","",'Contracts Y2'!J15) | N8: =IF(N$4="","",'Contracts Y2'!J16) | O8: =IF(O$4="","",'Contracts Y2'!J17) | P8: =IF(P$4="","",'Contracts Y2'!J18) | Q8: =IF(Q$4="","",'Contracts Y2'!J19) | R8: =IF(R$4="","",'Contracts Y2'!J20) | S8: =IF(S$4="","",'Contracts Y2'!J21) | T8: =IF(T$4="","",'Contracts Y2'!J22) | U8: =IF(U$4="","",'Contracts Y2'!J23) | V8: =IF(V$4="","",'Contracts Y2'!J24) | W8: =IF(W$4="","",'Contracts Y2'!J25) | X8: =IF(X$4="","",'Contracts Y2'!J26) | Y8: =IF(Y$4="","",'Contracts Y2'!J27) | Z8: =IF(Z$4="","",'Contracts Y2'!J28) | AA8: =IF(AA$4="","",'Contracts Y2'!J29) | AB8: =IF(AB$4="","",'Contracts Y2'!J30) | AC8: =IF(AC$4="","",'Contracts Y2'!J31) | AD8: =IF(AD$4="","",'Contracts Y2'!J32) | AE8: =IF(AE$4="","",'Contracts Y2'!J33) | AF8: =IF(AF$4="","",'Contracts Y2'!J34)
A9: Less other direct contract expenses | B9: =SUM('Contracts Y2'!K$5:K$34) | C9: =IF(C$4="","",N('Contracts Y2'!K5)) | D9: =IF(D$4="","",N('Contracts Y2'!K6)) | E9: =IF(E$4="","",N('Contracts Y2'!K7)) | F9: =IF(F$4="","",N('Contracts Y2'!K8)) | G9: =IF(G$4="","",N('Contracts Y2'!K9)) | H9: =IF(H$4="","",N('Contracts Y2'!K10)) | I9: =IF(I$4="","",N('Contracts Y2'!K11)) | J9: =IF(J$4="","",N('Contracts Y2'!K12)) | K9: =IF(K$4="","",N('Contracts Y2'!K13)) | L9: =IF(L$4="","",N('Contracts Y2'!K14)) | M9: =IF(M$4="","",N('Contracts Y2'!K15)) | N9: =IF(N$4="","",N('Contracts Y2'!K16)) | O9: =IF(O$4="","",N('Contracts Y2'!K17)) | P9: =IF(P$4="","",N('Contracts Y2'!K18)) | Q9: =IF(Q$4="","",N('Contracts Y2'!K19)) | R9: =IF(R$4="","",N('Contracts Y2'!K20)) | S9: =IF(S$4="","",N('Contracts Y2'!K21)) | T9: =IF(T$4="","",N('Contracts Y2'!K22)) | U9: =IF(U$4="","",N('Contracts Y2'!K23)) | V9: =IF(V$4="","",N('Contracts Y2'!K24)) | W9: =IF(W$4="","",N('Contracts Y2'!K25)) | X9: =IF(X$4="","",N('Contracts Y2'!K26)) | Y9: =IF(Y$4="","",N('Contracts Y2'!K27)) | Z9: =IF(Z$4="","",N('Contracts Y2'!K28)) | AA9: =IF(AA$4="","",N('Contracts Y2'!K29)) | AB9: =IF(AB$4="","",N('Contracts Y2'!K30)) | AC9: =IF(AC$4="","",N('Contracts Y2'!K31)) | AD9: =IF(AD$4="","",N('Contracts Y2'!K32)) | AE9: =IF(AE$4="","",N('Contracts Y2'!K33)) | AF9: =IF(AF$4="","",N('Contracts Y2'!K34))
A10: Contribution margin | B10: =B6-B7-B8-B9 | C10: =IF(C$4="","",C6-C7-C8-C9) | D10: =IF(D$4="","",D6-D7-D8-D9) | E10: =IF(E$4="","",E6-E7-E8-E9) | F10: =IF(F$4="","",F6-F7-F8-F9) | G10: =IF(G$4="","",G6-G7-G8-G9) | H10: =IF(H$4="","",H6-H7-H8-H9) | I10: =IF(I$4="","",I6-I7-I8-I9) | J10: =IF(J$4="","",J6-J7-J8-J9) | ... AF10: =IF(AF$4="","",AF6-AF7-AF8-AF9)
A11: Less fixed operating expenses | B11: =FixedTotal
A12: Operating profit | B12: =B10-B11
A13: CM % | B13: =IF(B6=0,"",B10/B6) | C13: =IF(N(C6)=0,"",C10/C6) | D13: =IF(N(D6)=0,"",D10/D6) | E13: =IF(N(E6)=0,"",E10/E6) | F13: =IF(N(F6)=0,"",F10/F6) | G13: =IF(N(G6)=0,"",G10/G6) | H13: =IF(N(H6)=0,"",H10/H6) | I13: =IF(N(I6)=0,"",I10/I6) | J13: =IF(N(J6)=0,"",J10/J6) | ... AF13: =IF(N(AF6)=0,"",AF10/AF6)
A14: Operating margin % | B14: =IF(B6=0,"",B12/B6)
A15: Share of market (revenue / market size) | B15: =IF(N(Inputs!$B$34)=0,"",B6/Inputs!$B$34) | C15: =IF(OR(C$4="",N(Inputs!$B$34)=0),"",C6/Inputs!$B$34) | D15: =IF(OR(D$4="",N(Inputs!$B$34)=0),"",D6/Inputs!$B$34) | E15: =IF(OR(E$4="",N(Inputs!$B$34)=0),"",E6/Inputs!$B$34) | F15: =IF(OR(F$4="",N(Inputs!$B$34)=0),"",F6/Inputs!$B$34) | G15: =IF(OR(G$4="",N(Inputs!$B$34)=0),"",G6/Inputs!$B$34) | H15: =IF(OR(H$4="",N(Inputs!$B$34)=0),"",H6/Inputs!$B$34) | I15: =IF(OR(I$4="",N(Inputs!$B$34)=0),"",I6/Inputs!$B$34) | J15: =IF(OR(J$4="",N(Inputs!$B$34)=0),"",J6/Inputs!$B$34) | ... AF15: =IF(OR(AF$4="",N(Inputs!$B$34)=0),"",AF6/Inputs!$B$34)
A17: Fixed expenses, operating profit and operating margin are reported for the year only, not per contract.

Sheet Contracts Y3
A1: Year 3 contracts won
A2: Type Contract ID, Spec, Accepted qty and Price (blue cells) in any empty row; every other column calculates. Each contract is its own purchase order.
A3: Orange price = outside the case price range (Inputs B8:B9). Other direct defaults to 0.
A4: Contract ID | B4: Spec | C4: Accepted qty (BB) | D4: Price per BB ($) | E4: Production qty (BB) | F4: Rejected qty (BB) | G4: RM price per BB ($) | H4: Revenue ($) | I4: Raw materials ($) | J4: Wages ($) | K4: Other direct ($) | L4: Contribution margin ($) | M4: CM % | N4: Break-even price per accepted BB ($) | O4: Price vs break-even ($)
E5: =IF($A5="","",ROUNDUP(C5/(1-RejRate),0)) | F5: =IF($A5="","",E5-C5) | G5: =IF($A5="","",IF(B5="Gold",GoldPrice,INDEX(TierPrices,MATCH(E5,TierQty,1),MATCH(B5,TierSpecs,0)))) | H5: =IF($A5="","",C5*D5) | I5: =IF($A5="","",E5*G5) | J5: =IF($A5="","",I5*WageCoef) | L5: =IF($A5="","",H5-I5-J5-N(K5)) | M5: =IF(OR($A5="",N(H5)=0),"",L5/H5) | N5: =IF(OR($A5="",N(C5)=0),"",(E5*G5*(1+WageCoef)+N(K5))/C5) | O5: =IF(OR($A5="",N5=""),"",D5-N5)
E6: =IF($A6="","",ROUNDUP(C6/(1-RejRate),0)) | F6: =IF($A6="","",E6-C6) | G6: =IF($A6="","",IF(B6="Gold",GoldPrice,INDEX(TierPrices,MATCH(E6,TierQty,1),MATCH(B6,TierSpecs,0)))) | H6: =IF($A6="","",C6*D6) | I6: =IF($A6="","",E6*G6) | J6: =IF($A6="","",I6*WageCoef) | L6: =IF($A6="","",H6-I6-J6-N(K6)) | M6: =IF(OR($A6="",N(H6)=0),"",L6/H6) | N6: =IF(OR($A6="",N(C6)=0),"",(E6*G6*(1+WageCoef)+N(K6))/C6) | O6: =IF(OR($A6="",N6=""),"",D6-N6)
E7: =IF($A7="","",ROUNDUP(C7/(1-RejRate),0)) | F7: =IF($A7="","",E7-C7) | G7: =IF($A7="","",IF(B7="Gold",GoldPrice,INDEX(TierPrices,MATCH(E7,TierQty,1),MATCH(B7,TierSpecs,0)))) | H7: =IF($A7="","",C7*D7) | I7: =IF($A7="","",E7*G7) | J7: =IF($A7="","",I7*WageCoef) | L7: =IF($A7="","",H7-I7-J7-N(K7)) | M7: =IF(OR($A7="",N(H7)=0),"",L7/H7) | N7: =IF(OR($A7="",N(C7)=0),"",(E7*G7*(1+WageCoef)+N(K7))/C7) | O7: =IF(OR($A7="",N7=""),"",D7-N7)
E8: =IF($A8="","",ROUNDUP(C8/(1-RejRate),0)) | F8: =IF($A8="","",E8-C8) | G8: =IF($A8="","",IF(B8="Gold",GoldPrice,INDEX(TierPrices,MATCH(E8,TierQty,1),MATCH(B8,TierSpecs,0)))) | H8: =IF($A8="","",C8*D8) | I8: =IF($A8="","",E8*G8) | J8: =IF($A8="","",I8*WageCoef) | L8: =IF($A8="","",H8-I8-J8-N(K8)) | M8: =IF(OR($A8="",N(H8)=0),"",L8/H8) | N8: =IF(OR($A8="",N(C8)=0),"",(E8*G8*(1+WageCoef)+N(K8))/C8) | O8: =IF(OR($A8="",N8=""),"",D8-N8)
E9: =IF($A9="","",ROUNDUP(C9/(1-RejRate),0)) | F9: =IF($A9="","",E9-C9) | G9: =IF($A9="","",IF(B9="Gold",GoldPrice,INDEX(TierPrices,MATCH(E9,TierQty,1),MATCH(B9,TierSpecs,0)))) | H9: =IF($A9="","",C9*D9) | I9: =IF($A9="","",E9*G9) | J9: =IF($A9="","",I9*WageCoef) | L9: =IF($A9="","",H9-I9-J9-N(K9)) | M9: =IF(OR($A9="",N(H9)=0),"",L9/H9) | N9: =IF(OR($A9="",N(C9)=0),"",(E9*G9*(1+WageCoef)+N(K9))/C9) | O9: =IF(OR($A9="",N9=""),"",D9-N9)
E10: =IF($A10="","",ROUNDUP(C10/(1-RejRate),0)) | F10: =IF($A10="","",E10-C10) | G10: =IF($A10="","",IF(B10="Gold",GoldPrice,INDEX(TierPrices,MATCH(E10,TierQty,1),MATCH(B10,TierSpecs,0)))) | H10: =IF($A10="","",C10*D10) | I10: =IF($A10="","",E10*G10) | J10: =IF($A10="","",I10*WageCoef) | L10: =IF($A10="","",H10-I10-J10-N(K10)) | M10: =IF(OR($A10="",N(H10)=0),"",L10/H10) | N10: =IF(OR($A10="",N(C10)=0),"",(E10*G10*(1+WageCoef)+N(K10))/C10) | O10: =IF(OR($A10="",N10=""),"",D10-N10)
E11: =IF($A11="","",ROUNDUP(C11/(1-RejRate),0)) | F11: =IF($A11="","",E11-C11) | G11: =IF($A11="","",IF(B11="Gold",GoldPrice,INDEX(TierPrices,MATCH(E11,TierQty,1),MATCH(B11,TierSpecs,0)))) | H11: =IF($A11="","",C11*D11) | I11: =IF($A11="","",E11*G11) | J11: =IF($A11="","",I11*WageCoef) | L11: =IF($A11="","",H11-I11-J11-N(K11)) | M11: =IF(OR($A11="",N(H11)=0),"",L11/H11) | N11: =IF(OR($A11="",N(C11)=0),"",(E11*G11*(1+WageCoef)+N(K11))/C11) | O11: =IF(OR($A11="",N11=""),"",D11-N11)
E12: =IF($A12="","",ROUNDUP(C12/(1-RejRate),0)) | F12: =IF($A12="","",E12-C12) | G12: =IF($A12="","",IF(B12="Gold",GoldPrice,INDEX(TierPrices,MATCH(E12,TierQty,1),MATCH(B12,TierSpecs,0)))) | H12: =IF($A12="","",C12*D12) | I12: =IF($A12="","",E12*G12) | J12: =IF($A12="","",I12*WageCoef) | L12: =IF($A12="","",H12-I12-J12-N(K12)) | M12: =IF(OR($A12="",N(H12)=0),"",L12/H12) | N12: =IF(OR($A12="",N(C12)=0),"",(E12*G12*(1+WageCoef)+N(K12))/C12) | O12: =IF(OR($A12="",N12=""),"",D12-N12)
E13: =IF($A13="","",ROUNDUP(C13/(1-RejRate),0)) | F13: =IF($A13="","",E13-C13) | G13: =IF($A13="","",IF(B13="Gold",GoldPrice,INDEX(TierPrices,MATCH(E13,TierQty,1),MATCH(B13,TierSpecs,0)))) | H13: =IF($A13="","",C13*D13) | I13: =IF($A13="","",E13*G13) | J13: =IF($A13="","",I13*WageCoef) | L13: =IF($A13="","",H13-I13-J13-N(K13)) | M13: =IF(OR($A13="",N(H13)=0),"",L13/H13) | N13: =IF(OR($A13="",N(C13)=0),"",(E13*G13*(1+WageCoef)+N(K13))/C13) | O13: =IF(OR($A13="",N13=""),"",D13-N13)
E14: =IF($A14="","",ROUNDUP(C14/(1-RejRate),0)) | F14: =IF($A14="","",E14-C14) | G14: =IF($A14="","",IF(B14="Gold",GoldPrice,INDEX(TierPrices,MATCH(E14,TierQty,1),MATCH(B14,TierSpecs,0)))) | H14: =IF($A14="","",C14*D14) | I14: =IF($A14="","",E14*G14) | J14: =IF($A14="","",I14*WageCoef) | L14: =IF($A14="","",H14-I14-J14-N(K14)) | M14: =IF(OR($A14="",N(H14)=0),"",L14/H14) | N14: =IF(OR($A14="",N(C14)=0),"",(E14*G14*(1+WageCoef)+N(K14))/C14) | O14: =IF(OR($A14="",N14=""),"",D14-N14)
E15: =IF($A15="","",ROUNDUP(C15/(1-RejRate),0)) | F15: =IF($A15="","",E15-C15) | G15: =IF($A15="","",IF(B15="Gold",GoldPrice,INDEX(TierPrices,MATCH(E15,TierQty,1),MATCH(B15,TierSpecs,0)))) | H15: =IF($A15="","",C15*D15) | I15: =IF($A15="","",E15*G15) | J15: =IF($A15="","",I15*WageCoef) | L15: =IF($A15="","",H15-I15-J15-N(K15)) | M15: =IF(OR($A15="",N(H15)=0),"",L15/H15) | N15: =IF(OR($A15="",N(C15)=0),"",(E15*G15*(1+WageCoef)+N(K15))/C15) | O15: =IF(OR($A15="",N15=""),"",D15-N15)
E16: =IF($A16="","",ROUNDUP(C16/(1-RejRate),0)) | F16: =IF($A16="","",E16-C16) | G16: =IF($A16="","",IF(B16="Gold",GoldPrice,INDEX(TierPrices,MATCH(E16,TierQty,1),MATCH(B16,TierSpecs,0)))) | H16: =IF($A16="","",C16*D16) | I16: =IF($A16="","",E16*G16) | J16: =IF($A16="","",I16*WageCoef) | L16: =IF($A16="","",H16-I16-J16-N(K16)) | M16: =IF(OR($A16="",N(H16)=0),"",L16/H16) | N16: =IF(OR($A16="",N(C16)=0),"",(E16*G16*(1+WageCoef)+N(K16))/C16) | O16: =IF(OR($A16="",N16=""),"",D16-N16)
... E34: =IF($A34="","",ROUNDUP(C34/(1-RejRate),0)) | F34: =IF($A34="","",E34-C34) | G34: =IF($A34="","",IF(B34="Gold",GoldPrice,INDEX(TierPrices,MATCH(E34,TierQty,1),MATCH(B34,TierSpecs,0)))) | H34: =IF($A34="","",C34*D34) | I34: =IF($A34="","",E34*G34) | J34: =IF($A34="","",I34*WageCoef) | L34: =IF($A34="","",H34-I34-J34-N(K34)) | M34: =IF(OR($A34="",N(H34)=0),"",L34/H34) | N34: =IF(OR($A34="",N(C34)=0),"",(E34*G34*(1+WageCoef)+N(K34))/C34) | O34: =IF(OR($A34="",N34=""),"",D34-N34)
A36: Total | C36: =SUM(C5:C34) | E36: =SUM(E5:E34) | F36: =SUM(F5:F34) | H36: =SUM(H5:H34) | I36: =SUM(I5:I34) | J36: =SUM(J5:J34) | K36: =SUM(K5:K34) | L36: =SUM(L5:L34) | M36: =IF(N(H36)=0,"",L36/H36)

Sheet P&L Y3
A1: Year 3 profit and loss
A2: Contract columns read Contracts Y3 row by row; blank columns are unused contract rows. Year total sums the whole contract range. Costs shown as positive amounts that are subtracted.
A4: Contract | B4: Year total | C4: =IF('Contracts Y3'!$A5="","",'Contracts Y3'!$A5) | D4: =IF('Contracts Y3'!$A6="","",'Contracts Y3'!$A6) | E4: =IF('Contracts Y3'!$A7="","",'Contracts Y3'!$A7) | F4: =IF('Contracts Y3'!$A8="","",'Contracts Y3'!$A8) | G4: =IF('Contracts Y3'!$A9="","",'Contracts Y3'!$A9) | H4: =IF('Contracts Y3'!$A10="","",'Contracts Y3'!$A10) | I4: =IF('Contracts Y3'!$A11="","",'Contracts Y3'!$A11) | J4: =IF('Contracts Y3'!$A12="","",'Contracts Y3'!$A12) | K4: =IF('Contracts Y3'!$A13="","",'Contracts Y3'!$A13) | L4: =IF('Contracts Y3'!$A14="","",'Contracts Y3'!$A14) | M4: =IF('Contracts Y3'!$A15="","",'Contracts Y3'!$A15) | N4: =IF('Contracts Y3'!$A16="","",'Contracts Y3'!$A16) | O4: =IF('Contracts Y3'!$A17="","",'Contracts Y3'!$A17) | P4: =IF('Contracts Y3'!$A18="","",'Contracts Y3'!$A18) | Q4: =IF('Contracts Y3'!$A19="","",'Contracts Y3'!$A19) | R4: =IF('Contracts Y3'!$A20="","",'Contracts Y3'!$A20) | S4: =IF('Contracts Y3'!$A21="","",'Contracts Y3'!$A21) | T4: =IF('Contracts Y3'!$A22="","",'Contracts Y3'!$A22) | U4: =IF('Contracts Y3'!$A23="","",'Contracts Y3'!$A23) | V4: =IF('Contracts Y3'!$A24="","",'Contracts Y3'!$A24) | W4: =IF('Contracts Y3'!$A25="","",'Contracts Y3'!$A25) | X4: =IF('Contracts Y3'!$A26="","",'Contracts Y3'!$A26) | Y4: =IF('Contracts Y3'!$A27="","",'Contracts Y3'!$A27) | Z4: =IF('Contracts Y3'!$A28="","",'Contracts Y3'!$A28) | AA4: =IF('Contracts Y3'!$A29="","",'Contracts Y3'!$A29) | AB4: =IF('Contracts Y3'!$A30="","",'Contracts Y3'!$A30) | AC4: =IF('Contracts Y3'!$A31="","",'Contracts Y3'!$A31) | AD4: =IF('Contracts Y3'!$A32="","",'Contracts Y3'!$A32) | AE4: =IF('Contracts Y3'!$A33="","",'Contracts Y3'!$A33) | AF4: =IF('Contracts Y3'!$A34="","",'Contracts Y3'!$A34)
A5: Spec | C5: =IF('Contracts Y3'!$A5="","",'Contracts Y3'!$B5) | D5: =IF('Contracts Y3'!$A6="","",'Contracts Y3'!$B6) | E5: =IF('Contracts Y3'!$A7="","",'Contracts Y3'!$B7) | F5: =IF('Contracts Y3'!$A8="","",'Contracts Y3'!$B8) | G5: =IF('Contracts Y3'!$A9="","",'Contracts Y3'!$B9) | H5: =IF('Contracts Y3'!$A10="","",'Contracts Y3'!$B10) | I5: =IF('Contracts Y3'!$A11="","",'Contracts Y3'!$B11) | J5: =IF('Contracts Y3'!$A12="","",'Contracts Y3'!$B12) | K5: =IF('Contracts Y3'!$A13="","",'Contracts Y3'!$B13) | L5: =IF('Contracts Y3'!$A14="","",'Contracts Y3'!$B14) | M5: =IF('Contracts Y3'!$A15="","",'Contracts Y3'!$B15) | N5: =IF('Contracts Y3'!$A16="","",'Contracts Y3'!$B16) | O5: =IF('Contracts Y3'!$A17="","",'Contracts Y3'!$B17) | P5: =IF('Contracts Y3'!$A18="","",'Contracts Y3'!$B18) | Q5: =IF('Contracts Y3'!$A19="","",'Contracts Y3'!$B19) | R5: =IF('Contracts Y3'!$A20="","",'Contracts Y3'!$B20) | S5: =IF('Contracts Y3'!$A21="","",'Contracts Y3'!$B21) | T5: =IF('Contracts Y3'!$A22="","",'Contracts Y3'!$B22) | U5: =IF('Contracts Y3'!$A23="","",'Contracts Y3'!$B23) | V5: =IF('Contracts Y3'!$A24="","",'Contracts Y3'!$B24) | W5: =IF('Contracts Y3'!$A25="","",'Contracts Y3'!$B25) | X5: =IF('Contracts Y3'!$A26="","",'Contracts Y3'!$B26) | Y5: =IF('Contracts Y3'!$A27="","",'Contracts Y3'!$B27) | Z5: =IF('Contracts Y3'!$A28="","",'Contracts Y3'!$B28) | AA5: =IF('Contracts Y3'!$A29="","",'Contracts Y3'!$B29) | AB5: =IF('Contracts Y3'!$A30="","",'Contracts Y3'!$B30) | AC5: =IF('Contracts Y3'!$A31="","",'Contracts Y3'!$B31) | AD5: =IF('Contracts Y3'!$A32="","",'Contracts Y3'!$B32) | AE5: =IF('Contracts Y3'!$A33="","",'Contracts Y3'!$B33) | AF5: =IF('Contracts Y3'!$A34="","",'Contracts Y3'!$B34)
A6: Contract revenue | B6: =SUM('Contracts Y3'!H$5:H$34) | C6: =IF(C$4="","",'Contracts Y3'!H5) | D6: =IF(D$4="","",'Contracts Y3'!H6) | E6: =IF(E$4="","",'Contracts Y3'!H7) | F6: =IF(F$4="","",'Contracts Y3'!H8) | G6: =IF(G$4="","",'Contracts Y3'!H9) | H6: =IF(H$4="","",'Contracts Y3'!H10) | I6: =IF(I$4="","",'Contracts Y3'!H11) | J6: =IF(J$4="","",'Contracts Y3'!H12) | K6: =IF(K$4="","",'Contracts Y3'!H13) | L6: =IF(L$4="","",'Contracts Y3'!H14) | M6: =IF(M$4="","",'Contracts Y3'!H15) | N6: =IF(N$4="","",'Contracts Y3'!H16) | O6: =IF(O$4="","",'Contracts Y3'!H17) | P6: =IF(P$4="","",'Contracts Y3'!H18) | Q6: =IF(Q$4="","",'Contracts Y3'!H19) | R6: =IF(R$4="","",'Contracts Y3'!H20) | S6: =IF(S$4="","",'Contracts Y3'!H21) | T6: =IF(T$4="","",'Contracts Y3'!H22) | U6: =IF(U$4="","",'Contracts Y3'!H23) | V6: =IF(V$4="","",'Contracts Y3'!H24) | W6: =IF(W$4="","",'Contracts Y3'!H25) | X6: =IF(X$4="","",'Contracts Y3'!H26) | Y6: =IF(Y$4="","",'Contracts Y3'!H27) | Z6: =IF(Z$4="","",'Contracts Y3'!H28) | AA6: =IF(AA$4="","",'Contracts Y3'!H29) | AB6: =IF(AB$4="","",'Contracts Y3'!H30) | AC6: =IF(AC$4="","",'Contracts Y3'!H31) | AD6: =IF(AD$4="","",'Contracts Y3'!H32) | AE6: =IF(AE$4="","",'Contracts Y3'!H33) | AF6: =IF(AF$4="","",'Contracts Y3'!H34)
A7: Less raw materials used | B7: =SUM('Contracts Y3'!I$5:I$34) | C7: =IF(C$4="","",'Contracts Y3'!I5) | D7: =IF(D$4="","",'Contracts Y3'!I6) | E7: =IF(E$4="","",'Contracts Y3'!I7) | F7: =IF(F$4="","",'Contracts Y3'!I8) | G7: =IF(G$4="","",'Contracts Y3'!I9) | H7: =IF(H$4="","",'Contracts Y3'!I10) | I7: =IF(I$4="","",'Contracts Y3'!I11) | J7: =IF(J$4="","",'Contracts Y3'!I12) | K7: =IF(K$4="","",'Contracts Y3'!I13) | L7: =IF(L$4="","",'Contracts Y3'!I14) | M7: =IF(M$4="","",'Contracts Y3'!I15) | N7: =IF(N$4="","",'Contracts Y3'!I16) | O7: =IF(O$4="","",'Contracts Y3'!I17) | P7: =IF(P$4="","",'Contracts Y3'!I18) | Q7: =IF(Q$4="","",'Contracts Y3'!I19) | R7: =IF(R$4="","",'Contracts Y3'!I20) | S7: =IF(S$4="","",'Contracts Y3'!I21) | T7: =IF(T$4="","",'Contracts Y3'!I22) | U7: =IF(U$4="","",'Contracts Y3'!I23) | V7: =IF(V$4="","",'Contracts Y3'!I24) | W7: =IF(W$4="","",'Contracts Y3'!I25) | X7: =IF(X$4="","",'Contracts Y3'!I26) | Y7: =IF(Y$4="","",'Contracts Y3'!I27) | Z7: =IF(Z$4="","",'Contracts Y3'!I28) | AA7: =IF(AA$4="","",'Contracts Y3'!I29) | AB7: =IF(AB$4="","",'Contracts Y3'!I30) | AC7: =IF(AC$4="","",'Contracts Y3'!I31) | AD7: =IF(AD$4="","",'Contracts Y3'!I32) | AE7: =IF(AE$4="","",'Contracts Y3'!I33) | AF7: =IF(AF$4="","",'Contracts Y3'!I34)
A8: Less production wages | B8: =SUM('Contracts Y3'!J$5:J$34) | C8: =IF(C$4="","",'Contracts Y3'!J5) | D8: =IF(D$4="","",'Contracts Y3'!J6) | E8: =IF(E$4="","",'Contracts Y3'!J7) | F8: =IF(F$4="","",'Contracts Y3'!J8) | G8: =IF(G$4="","",'Contracts Y3'!J9) | H8: =IF(H$4="","",'Contracts Y3'!J10) | I8: =IF(I$4="","",'Contracts Y3'!J11) | J8: =IF(J$4="","",'Contracts Y3'!J12) | K8: =IF(K$4="","",'Contracts Y3'!J13) | L8: =IF(L$4="","",'Contracts Y3'!J14) | M8: =IF(M$4="","",'Contracts Y3'!J15) | N8: =IF(N$4="","",'Contracts Y3'!J16) | O8: =IF(O$4="","",'Contracts Y3'!J17) | P8: =IF(P$4="","",'Contracts Y3'!J18) | Q8: =IF(Q$4="","",'Contracts Y3'!J19) | R8: =IF(R$4="","",'Contracts Y3'!J20) | S8: =IF(S$4="","",'Contracts Y3'!J21) | T8: =IF(T$4="","",'Contracts Y3'!J22) | U8: =IF(U$4="","",'Contracts Y3'!J23) | V8: =IF(V$4="","",'Contracts Y3'!J24) | W8: =IF(W$4="","",'Contracts Y3'!J25) | X8: =IF(X$4="","",'Contracts Y3'!J26) | Y8: =IF(Y$4="","",'Contracts Y3'!J27) | Z8: =IF(Z$4="","",'Contracts Y3'!J28) | AA8: =IF(AA$4="","",'Contracts Y3'!J29) | AB8: =IF(AB$4="","",'Contracts Y3'!J30) | AC8: =IF(AC$4="","",'Contracts Y3'!J31) | AD8: =IF(AD$4="","",'Contracts Y3'!J32) | AE8: =IF(AE$4="","",'Contracts Y3'!J33) | AF8: =IF(AF$4="","",'Contracts Y3'!J34)
A9: Less other direct contract expenses | B9: =SUM('Contracts Y3'!K$5:K$34) | C9: =IF(C$4="","",N('Contracts Y3'!K5)) | D9: =IF(D$4="","",N('Contracts Y3'!K6)) | E9: =IF(E$4="","",N('Contracts Y3'!K7)) | F9: =IF(F$4="","",N('Contracts Y3'!K8)) | G9: =IF(G$4="","",N('Contracts Y3'!K9)) | H9: =IF(H$4="","",N('Contracts Y3'!K10)) | I9: =IF(I$4="","",N('Contracts Y3'!K11)) | J9: =IF(J$4="","",N('Contracts Y3'!K12)) | K9: =IF(K$4="","",N('Contracts Y3'!K13)) | L9: =IF(L$4="","",N('Contracts Y3'!K14)) | M9: =IF(M$4="","",N('Contracts Y3'!K15)) | N9: =IF(N$4="","",N('Contracts Y3'!K16)) | O9: =IF(O$4="","",N('Contracts Y3'!K17)) | P9: =IF(P$4="","",N('Contracts Y3'!K18)) | Q9: =IF(Q$4="","",N('Contracts Y3'!K19)) | R9: =IF(R$4="","",N('Contracts Y3'!K20)) | S9: =IF(S$4="","",N('Contracts Y3'!K21)) | T9: =IF(T$4="","",N('Contracts Y3'!K22)) | U9: =IF(U$4="","",N('Contracts Y3'!K23)) | V9: =IF(V$4="","",N('Contracts Y3'!K24)) | W9: =IF(W$4="","",N('Contracts Y3'!K25)) | X9: =IF(X$4="","",N('Contracts Y3'!K26)) | Y9: =IF(Y$4="","",N('Contracts Y3'!K27)) | Z9: =IF(Z$4="","",N('Contracts Y3'!K28)) | AA9: =IF(AA$4="","",N('Contracts Y3'!K29)) | AB9: =IF(AB$4="","",N('Contracts Y3'!K30)) | AC9: =IF(AC$4="","",N('Contracts Y3'!K31)) | AD9: =IF(AD$4="","",N('Contracts Y3'!K32)) | AE9: =IF(AE$4="","",N('Contracts Y3'!K33)) | AF9: =IF(AF$4="","",N('Contracts Y3'!K34))
A10: Contribution margin | B10: =B6-B7-B8-B9 | C10: =IF(C$4="","",C6-C7-C8-C9) | D10: =IF(D$4="","",D6-D7-D8-D9) | E10: =IF(E$4="","",E6-E7-E8-E9) | F10: =IF(F$4="","",F6-F7-F8-F9) | G10: =IF(G$4="","",G6-G7-G8-G9) | H10: =IF(H$4="","",H6-H7-H8-H9) | I10: =IF(I$4="","",I6-I7-I8-I9) | J10: =IF(J$4="","",J6-J7-J8-J9) | ... AF10: =IF(AF$4="","",AF6-AF7-AF8-AF9)
A11: Less fixed operating expenses | B11: =FixedTotal
A12: Operating profit | B12: =B10-B11
A13: CM % | B13: =IF(B6=0,"",B10/B6) | C13: =IF(N(C6)=0,"",C10/C6) | D13: =IF(N(D6)=0,"",D10/D6) | E13: =IF(N(E6)=0,"",E10/E6) | F13: =IF(N(F6)=0,"",F10/F6) | G13: =IF(N(G6)=0,"",G10/G6) | H13: =IF(N(H6)=0,"",H10/H6) | I13: =IF(N(I6)=0,"",I10/I6) | J13: =IF(N(J6)=0,"",J10/J6) | ... AF13: =IF(N(AF6)=0,"",AF10/AF6)
A14: Operating margin % | B14: =IF(B6=0,"",B12/B6)
A15: Share of market (revenue / market size) | B15: =IF(N(Inputs!$B$35)=0,"",B6/Inputs!$B$35) | C15: =IF(OR(C$4="",N(Inputs!$B$35)=0),"",C6/Inputs!$B$35) | D15: =IF(OR(D$4="",N(Inputs!$B$35)=0),"",D6/Inputs!$B$35) | E15: =IF(OR(E$4="",N(Inputs!$B$35)=0),"",E6/Inputs!$B$35) | F15: =IF(OR(F$4="",N(Inputs!$B$35)=0),"",F6/Inputs!$B$35) | G15: =IF(OR(G$4="",N(Inputs!$B$35)=0),"",G6/Inputs!$B$35) | H15: =IF(OR(H$4="",N(Inputs!$B$35)=0),"",H6/Inputs!$B$35) | I15: =IF(OR(I$4="",N(Inputs!$B$35)=0),"",I6/Inputs!$B$35) | J15: =IF(OR(J$4="",N(Inputs!$B$35)=0),"",J6/Inputs!$B$35) | ... AF15: =IF(OR(AF$4="",N(Inputs!$B$35)=0),"",AF6/Inputs!$B$35)
A17: Fixed expenses, operating profit and operating margin are reported for the year only, not per contract.
