Workbook

Sheet Inputs
A1: Ball Bearing Contract Auction - Inputs
A2: Blue = hard-coded input from the case brief. Yellow = decision/assumption you can change.
A4: Raw-material price per BB (applies to every BB in one purchase order)
A5: Qty from | B5: Qty to | C5: Blue | D5: Silver | E5: Copper
A6: 1 | B6: 10 | C6: 7000 | D6: 6500 | E6: 5500
A7: 11 | B7: 20 | C7: 6500 | D7: 6000 | E7: 5000
A8: 21 | B8: 30 | C8: 5500 | D8: 5500 | E8: 4000
A9: 31 | B9: 40 | C9: 5000 | D9: 4500 | E9: 3000
A10: 41 | B10: or more | C10: 4000 | D10: 3500 | E10: 2000
A11: Source: case brief, raw-material price table. Gold ($4,500-$5,500) is announced after the auction; no Gold contract was won.
A13: Rejection rate | D13: 0.15
A14: Wage coefficient (x raw materials) | D14: 1.8
A15: Other direct contract expenses per contract | D15: 0
A16: Combine same-spec contracts into one purchase order? (1 = yes, 0 = no) | D16: 1
A17: Year 1 market size | D17: 5300000
A19: Annual fixed operating expenses
A20: Factory rent | D20: 50000
A21: Management and administration | D21: 40000
A22: Production-machine maintenance | D22: 35000
A23: Utilities and insurance | D23: 20000
A24: Office and marketing | D24: 15000
A25: Depreciation | D25: 40000
A26: Total fixed operating expenses | D26: =SUM(D20:D25)

Sheet Contracts
A1: Year 1 contracts won (from the auction cards) and contract profitability
A2: Blue = values read from the won contract cards (handwritten winning price). All other cells are formulas.
A4: Contract | B4: Spec | C4: Qty accepted (BB) | D4: Winning price / BB | E4: Revenue | F4: BB to produce | G4: Purchase-order qty | H4: Raw-mat. price / BB | I4: Raw materials | J4: Production wages | K4: Other direct exp. | L4: Contribution margin | M4: CM % | N4: Break-even price / BB | O4: List price / BB | P4: Discount vs list
A5: 05 | B5: Silver | C5: 15 | D5: 18000 | E5: =C5*D5 | F5: =ROUNDUP(ROUND(C5/(1-Inputs!$D$13),6),0) | G5: =IF(Inputs!$D$16=1,SUMIF($B$5:$B$7,B5,$F$5:$F$7),F5) | H5: =INDEX(Inputs!$C$6:$E$10,MATCH(G5,Inputs!$A$6:$A$10,1),MATCH(B5,Inputs!$C$5:$E$5,0)) | I5: =F5*H5 | J5: =I5*Inputs!$D$14 | K5: =Inputs!$D$15 | L5: =E5-I5-J5-K5 | M5: =IF(E5=0,0,L5/E5) | N5: =(I5+J5+K5)/C5 | O5: 20000 | P5: =IF(O5=0,0,1-D5/O5)
A6: 08 | B6: Silver | C6: 40 | D6: 11000 | E6: =C6*D6 | F6: =ROUNDUP(ROUND(C6/(1-Inputs!$D$13),6),0) | G6: =IF(Inputs!$D$16=1,SUMIF($B$5:$B$7,B6,$F$5:$F$7),F6) | H6: =INDEX(Inputs!$C$6:$E$10,MATCH(G6,Inputs!$A$6:$A$10,1),MATCH(B6,Inputs!$C$5:$E$5,0)) | I6: =F6*H6 | J6: =I6*Inputs!$D$14 | K6: =Inputs!$D$15 | L6: =E6-I6-J6-K6 | M6: =IF(E6=0,0,L6/E6) | N6: =(I6+J6+K6)/C6 | O6: 20000 | P6: =IF(O6=0,0,1-D6/O6)
A7: 09 | B7: Copper | C7: 40 | D7: 6500 | E7: =C7*D7 | F7: =ROUNDUP(ROUND(C7/(1-Inputs!$D$13),6),0) | G7: =IF(Inputs!$D$16=1,SUMIF($B$5:$B$7,B7,$F$5:$F$7),F7) | H7: =INDEX(Inputs!$C$6:$E$10,MATCH(G7,Inputs!$A$6:$A$10,1),MATCH(B7,Inputs!$C$5:$E$5,0)) | I7: =F7*H7 | J7: =I7*Inputs!$D$14 | K7: =Inputs!$D$15 | L7: =E7-I7-J7-K7 | M7: =IF(E7=0,0,L7/E7) | N7: =(I7+J7+K7)/C7 | O7: 18000 | P7: =IF(O7=0,0,1-D7/O7)
A8: Total | C8: =SUM(C5:C7) | D8: =IF(C8=0,0,E8/C8) | E8: =SUM(E5:E7) | F8: =SUM(F5:F7) | I8: =SUM(I5:I7) | J8: =SUM(J5:J7) | K8: =SUM(K5:K7) | L8: =SUM(L5:L7) | M8: =IF(E8=0,0,L8/E8) | N8: =(I8+J8+K8)/C8
A10: Notes
A11: BB to produce = accepted qty / (1 - 15%), rounded up to the next whole BB (rejects still cost materials and wages).
A12: Purchase-order qty decides the raw-material price tier. With Inputs!D16 = 1 both Silver contracts share one order (18 + 48 = 66 BB).
A13: Break-even price = the lowest winning price per accepted BB that covers raw materials + wages (before fixed costs).
A14: Contract 09 card: the quantity line is struck through along with the price; quantity is taken as the printed 40 BB.

Sheet P&L
A1: Annual profit and loss statement
B3: Year 1
A4: Contract revenue | B4: =Contracts!E8
A5: Less raw materials used | B5: =-Contracts!I8
A6: Less production wages | B6: =-Contracts!J8
A7: Less other direct contract expenses | B7: =-Contracts!K8
A8: Contribution margin | B8: =SUM(B4:B7)
A9: Less fixed operating expenses | B9: =-Inputs!D26
A10: Operating profit | B10: =B8+B9
A12: Contribution-margin % | B12: =IF(B4=0,0,B8/B4)
A13: Operating-margin % | B13: =IF(B4=0,0,B10/B4)
A14: Cumulative operating profit | B14: =B10
A16: BB accepted by customers | B16: =Contracts!C8
A17: BB produced (incl. rejects) | B17: =Contracts!F8
A18: Share of Year 1 market (revenue) | B18: =IF(Inputs!D17=0,0,B4/Inputs!D17)
A19: Operating profit per accepted BB | B19: =IF(B16=0,0,B10/B16)
A21: Green = linked from another sheet. Change Inputs!D16 to 0 to see the P&L if every contract is ordered separately.
